omegi/__init__.py
omegi/decorator/OmegiDecorator.py
omegi/decorator/__init__.py
omegi/exporter/OmegiSpanExporter.py
omegi/exporter/__init__.py
omegi/util/OmegiDependencyInstrument.py
omegi/util/OmegiErrorSpanFormatter.py
omegi/util/OmegiSamplerSpanFormatter.py
omegi/util/OmegiTracingSetup.py
omegi/util/UtilFunction.py
omegi/util/__init__.py
omegi_python_instrumentation-0.1.5.dist-info/LICENSE.txt
omegi_python_instrumentation-0.1.5.dist-info/METADATA
omegi_python_instrumentation-0.1.5.dist-info/WHEEL
omegi_python_instrumentation-0.1.5.dist-info/top_level.txt
omegi_python_instrumentation-0.1.5.dist-info/RECORD
